README.md
setup.py
QM_Spider.egg-info/PKG-INFO
QM_Spider.egg-info/SOURCES.txt
QM_Spider.egg-info/dependency_links.txt
QM_Spider.egg-info/requires.txt
QM_Spider.egg-info/top_level.txt
doc/Makefile
doc/make.bat
doc/build/doctrees/environment.pickle
doc/build/doctrees/index.doctree
doc/build/doctrees/modules.doctree
doc/build/doctrees/qm_spider.doctree
doc/build/html/.buildinfo
doc/build/html/genindex.html
doc/build/html/index.html
doc/build/html/modules.html
doc/build/html/objects.inv
doc/build/html/py-modindex.html
doc/build/html/qm_spider.html
doc/build/html/search.html
doc/build/html/searchindex.js
doc/build/html/_sources/index.rst.txt
doc/build/html/_sources/modules.rst.txt
doc/build/html/_sources/qm_spider.rst.txt
doc/build/html/_static/basic.css
doc/build/html/_static/doctools.js
doc/build/html/_static/documentation_options.js
doc/build/html/_static/file.png
doc/build/html/_static/jquery-3.5.1.js
doc/build/html/_static/jquery.js
doc/build/html/_static/language_data.js
doc/build/html/_static/minus.png
doc/build/html/_static/plus.png
doc/build/html/_static/pygments.css
doc/build/html/_static/searchtools.js
doc/build/html/_static/underscore-1.3.1.js
doc/build/html/_static/underscore.js
doc/build/html/_static/css/badge_only.css
doc/build/html/_static/css/theme.css
doc/build/html/_static/css/fonts/Roboto-Slab-Bold.woff
doc/build/html/_static/css/fonts/Roboto-Slab-Bold.woff2
doc/build/html/_static/css/fonts/Roboto-Slab-Regular.woff
doc/build/html/_static/css/fonts/Roboto-Slab-Regular.woff2
doc/build/html/_static/css/fonts/fontawesome-webfont.eot
doc/build/html/_static/css/fonts/fontawesome-webfont.svg
doc/build/html/_static/css/fonts/fontawesome-webfont.ttf
doc/build/html/_static/css/fonts/fontawesome-webfont.woff
doc/build/html/_static/css/fonts/fontawesome-webfont.woff2
doc/build/html/_static/css/fonts/lato-bold-italic.woff
doc/build/html/_static/css/fonts/lato-bold-italic.woff2
doc/build/html/_static/css/fonts/lato-bold.woff
doc/build/html/_static/css/fonts/lato-bold.woff2
doc/build/html/_static/css/fonts/lato-normal-italic.woff
doc/build/html/_static/css/fonts/lato-normal-italic.woff2
