Metadata-Version: 2.1
Name: QM-Spider
Version: 0.0.150
Summary: QueueMaster Spider library
Home-page: https://github.com/ShellMonster/QM_Spider
Author: @道长
Author-email: ctrlf4@yeah.net
License: Apache License 2.0
Classifier: Programming Language :: Python :: 3
Classifier: License :: OSI Approved :: MIT License
Classifier: Operating System :: OS Independent
Requires-Python: >=3.5
